stealthy_requests/__init__.py
stealthy_requests/core.py
stealthy_requests-0.2.0.dist-info/LICENSE
stealthy_requests-0.2.0.dist-info/METADATA
stealthy_requests-0.2.0.dist-info/WHEEL
stealthy_requests-0.2.0.dist-info/top_level.txt
stealthy_requests-0.2.0.dist-info/RECORD
