Metadata-Version: 2.1
Name: stealthy_requests
Version: 0.2.0
Summary: A stealthy requests library using Selenium for bot detection bypass
Author: DEvin
Author-email: firi8228@gmail.com
Classifier: Programming Language :: Python :: 3
Classifier: License :: OSI Approved :: MIT License
Classifier: Operating System :: OS Independent
Requires-Python: >=3.6
License-File: LICENSE
Requires-Dist: selenium
Requires-Dist: undetected-chromedriver
Requires-Dist: fake-useragent
